{
  "persons": [
    {
      "name": "Arto Hellas",
      "number": "040-123456",
      "id": 1
    },
    {
      "name": "Ada Lovelace",
      "number": "39-44-5323523",
      "id": 2
    },
    {
      "name": "ses",
      "number": "12345",
      "id": 5
    },
    {
      "name": "312",
      "number": "sdfsdf",
      "id": 6
    },
    {
      "name": " sf",
      "number": "423",
      "id": 7
    },
    {
      "name": "sd",
      "number": "",
      "id": 8
    },
    {
      "name": "hjk",
      "number": "123",
      "id": 9
    },
    {
      "name": "tet",
      "number": "342",
      "id": 10
    },
    {
      "name": "as",
      "number": "qwe",
      "id": 11
    },
    {
      "name": "asd",
      "number": "23132",
      "id": 12
    }
  ]
}